setup.cfg
setup.py
colormap_dev/Colormap.py
colormap_dev/__init__.py
colormap_dev.egg-info/PKG-INFO
colormap_dev.egg-info/SOURCES.txt
colormap_dev.egg-info/dependency_links.txt
colormap_dev.egg-info/not-zip-safe
colormap_dev.egg-info/top_level.txt