Metadata-Version: 1.0
Name: colormap-dev
Version: 0.0
Summary: User defined colormaps in colormaps.dev
Home-page: UNKNOWN
Author: UNKNOWN
Author-email: kwang66@illinos.edu
License: UNKNOWN
Platform: UNKNOWN
